{"trial_id": "0032", "hyperparameters": {"space": [{"class_name": "Choice", "config": {"name": "activation", "default": "relu", "conditions": [], "values": ["relu", "tanh", "sigmoid", "softmax", "swish"], "ordered": false}}, {"class_name": "Int", "config": {"name": "first_units", "default": null, "conditions": [], "min_value": 1, "max_value": 512, "step": 5, "sampling": "linear"}}, {"class_name": "Int", "config": {"name": "num_layers", "default": null, "conditions": [], "min_value": 1, "max_value": 8, "step": 1, "sampling": "linear"}}, {"class_name": "Int", "config": {"name": "units_0", "default": null, "conditions": [], "min_value": 1, "max_value": 512, "step": 5, "sampling": "linear"}}, {"class_name": "Int", "config": {"name": "units_1", "default": null, "conditions": [], "min_value": 1, "max_value": 512, "step": 5, "sampling": "linear"}}, {"class_name": "Int", "config": {"name": "units_2", "default": null, "conditions": [], "min_value": 1, "max_value": 512, "step": 5, "sampling": "linear"}}, {"class_name": "Int", "config": {"name": "units_3", "default": null, "conditions": [], "min_value": 1, "max_value": 512, "step": 5, "sampling": "linear"}}, {"class_name": "Int", "config": {"name": "units_4", "default": null, "conditions": [], "min_value": 1, "max_value": 512, "step": 5, "sampling": "linear"}}, {"class_name": "Int", "config": {"name": "units_5", "default": null, "conditions": [], "min_value": 1, "max_value": 512, "step": 5, "sampling": "linear"}}, {"class_name": "Int", "config": {"name": "units_6", "default": null, "conditions": [], "min_value": 1, "max_value": 512, "step": 5, "sampling": "linear"}}, {"class_name": "Int", "config": {"name": "units_7", "default": null, "conditions": [], "min_value": 1, "max_value": 512, "step": 5, "sampling": "linear"}}], "values": {"activation": "tanh", "first_units": 456, "num_layers": 3, "units_0": 336, "units_1": 71, "units_2": 116, "units_3": 101, "units_4": 151, "units_5": 406, "units_6": 411, "units_7": 401, "tuner/epochs": 3, "tuner/initial_epoch": 0, "tuner/bracket": 2, "tuner/round": 0}}, "metrics": {"metrics": {"loss": {"direction": "min", "observations": [{"value": [0.7831050753593445], "step": 2}]}, "accuracy": {"direction": "max", "observations": [{"value": [0.5541480779647827], "step": 2}]}, "val_loss": {"direction": "min", "observations": [{"value": [0.7777318954467773], "step": 2}]}, "val_accuracy": {"direction": "max", "observations": [{"value": [0.5594666004180908], "step": 2}]}}}, "score": 0.5594666004180908, "best_step": 2, "status": "COMPLETED", "message": null}