{"trial_id": "0056", "hyperparameters": {"space": [{"class_name": "Choice", "config": {"name": "activation", "default": "relu", "conditions": [], "values": ["relu", "tanh", "sigmoid", "softmax", "swish"], "ordered": false}}, {"class_name": "Int", "config": {"name": "first_units", "default": null, "conditions": [], "min_value": 1, "max_value": 512, "step": 5, "sampling": "linear"}}, {"class_name": "Int", "config": {"name": "num_layers", "default": null, "conditions": [], "min_value": 1, "max_value": 8, "step": 1, "sampling": "linear"}}, {"class_name": "Int", "config": {"name": "units_0", "default": null, "conditions": [], "min_value": 1, "max_value": 512, "step": 5, "sampling": "linear"}}, {"class_name": "Int", "config": {"name": "units_1", "default": null, "conditions": [], "min_value": 1, "max_value": 512, "step": 5, "sampling": "linear"}}, {"class_name": "Int", "config": {"name": "units_2", "default": null, "conditions": [], "min_value": 1, "max_value": 512, "step": 5, "sampling": "linear"}}, {"class_name": "Int", "config": {"name": "units_3", "default": null, "conditions": [], "min_value": 1, "max_value": 512, "step": 5, "sampling": "linear"}}, {"class_name": "Int", "config": {"name": "units_4", "default": null, "conditions": [], "min_value": 1, "max_value": 512, "step": 5, "sampling": "linear"}}, {"class_name": "Int", "config": {"name": "units_5", "default": null, "conditions": [], "min_value": 1, "max_value": 512, "step": 5, "sampling": "linear"}}, {"class_name": "Int", "config": {"name": "units_6", "default": null, "conditions": [], "min_value": 1, "max_value": 512, "step": 5, "sampling": "linear"}}, {"class_name": "Int", "config": {"name": "units_7", "default": null, "conditions": [], "min_value": 1, "max_value": 512, "step": 5, "sampling": "linear"}}], "values": {"activation": "tanh", "first_units": 16, "num_layers": 6, "units_0": 316, "units_1": 56, "units_2": 246, "units_3": 281, "units_4": 166, "units_5": 331, "units_6": 391, "units_7": 61, "tuner/epochs": 20, "tuner/initial_epoch": 0, "tuner/bracket": 0, "tuner/round": 0}}, "metrics": {"metrics": {"loss": {"direction": "min", "observations": [{"value": [0.7769685387611389], "step": 16}]}, "accuracy": {"direction": "max", "observations": [{"value": [0.5660513639450073], "step": 16}]}, "val_loss": {"direction": "min", "observations": [{"value": [0.7713953852653503], "step": 16}]}, "val_accuracy": {"direction": "max", "observations": [{"value": [0.5721969604492188], "step": 16}]}}}, "score": 0.5721969604492188, "best_step": 16, "status": "COMPLETED", "message": null}